explicit_behave/__init__.py
explicit_behave/_steps.py
explicit_behave/db.py
explicit_behave/http.py
explicit_behave/mocks.py
explicit_behave/utils.py
django_explicit_behave-1.14.5.dist-info/METADATA
django_explicit_behave-1.14.5.dist-info/WHEEL
django_explicit_behave-1.14.5.dist-info/top_level.txt
django_explicit_behave-1.14.5.dist-info/RECORD
