Metadata-Version: 2.2
Name: django-explicit-behave
Version: 1.14.5
Summary: A collection of explicit behave steps for API testing
Home-page: https://github.com/MaurizioPilia/django-explicit-behave
Author: Maurizio Pilia, Javier Buzzi
Author-email: piliamaurizio@gmail.com, buzzi.javier@gmail.com
Classifier: Development Status :: 5 - Production/Stable
Classifier: Environment :: Web Environment
Classifier: Intended Audience :: Developers
Classifier: License :: OSI Approved :: BSD License
Classifier: Operating System :: OS Independent
Classifier: Programming Language :: Python
Classifier: Programming Language :: Python :: 3.6
Classifier: Programming Language :: Python :: 3.7
Classifier: Programming Language :: Python :: 3.8
Classifier: Programming Language :: Python :: 3.9
Classifier: Programming Language :: Python :: 3.10
Classifier: Programming Language :: Python :: 3.11
Classifier: Programming Language :: Python :: 3.12
Classifier: Framework :: Django
Requires-Python: >=3.6
Requires-Dist: behave>=1.2.6
Requires-Dist: Django>=1.11
Requires-Dist: djangorestframework>=3.9.1
Requires-Dist: freezegun>=0.3.11
Requires-Dist: PyYAML>=3.13
Requires-Dist: jq>=0.1.6
Requires-Dist: factory-boy>=2.12.0
Requires-Dist: model-bakery>=1.3.2
Requires-Dist: tabulate>=0.8.3
Dynamic: author
Dynamic: author-email
Dynamic: classifier
Dynamic: home-page
Dynamic: requires-dist
Dynamic: requires-python
Dynamic: summary
